Metadata-Version: 2.1
Name: wikiservice
Version: 0.1.1
Summary: Lightweight library to work with MediaWiki-API
Home-page: https://github.com/lrlunin/wikiservice
Author: Leonid Lunin
Author-email: lunin.leonid@gmail.com
License: UNKNOWN
Platform: UNKNOWN
Classifier: Programming Language :: Python :: 3
Classifier: License :: OSI Approved :: MIT License
Classifier: Operating System :: OS Independent
Requires-Python: >=3.6
